{
    "total": 1,
    "launches": [{
        "id": 1257,
        "name": "Elon Musk | IAC 2017",
        "windowstart": "September 29, 2017 04:30:00 UTC",
        "windowend": "September 29, 2017 05:30:00 UTC",
        "net": "September 29, 2017 04:30:00 UTC",
        "wsstamp": 1506659400,
        "westamp": 1506663000,
        "netstamp": 1506659400,
        "isostart": "20170929T043000Z",
        "isoend": "20170929T053000Z",
        "isonet": "20170929T043000Z",
        "status": 1,
        "inhold": 0,
        "tbdtime": 0,
        "vidURLs": ["http:\/\/www.spacex.com\/mars\/", "https://www.youtube.com/watch?v=S5V7R_se1Xc"],
        "vidURL": null,
        "infoURLs": [],
        "infoURL": null,
        "holdreason": null,
        "failreason": null,
        "tbddate": 0,
        "probability": -1,
        "hashtag": null,
        "location": {
            "pads": [{
                "id": 100,
                "name": "Adelaide Convention Centre, Adelaide, Australia",
                "infoURL": "",
                "wikiURL": "",
                "mapURL": "http:\/\/maps.google.com\/maps?q=-34.9213707,138.5939418",
                "latitude": -34.9213707,
                "longitude": 138.5939418,
                "agencies": [{
                    "id": 121,
                    "name": "SpaceX",
                    "abbrev": "SpX",
                    "countryCode": "USA",
                    "type": 3,
                    "infoURL": "http:\/\/www.spacex.com\/",
                    "wikiURL": "http:\/\/en.wikipedia.org\/wiki\/SpaceX",
                    "infoURLs": ["http:\/\/www.spacex.com\/"]
                }]
            }],
            "id": 18,
            "name": "Adelaide, Australia",
            "infoURL": "",
            "wikiURL": "",
            "countryCode": "AUS"
        },
        "rocket": {
            "id": 80,
            "name": "Elon Musk",
            "configuration": "9 Full Thrust",
            "familyname": "Musk",
            "agencies": [{
                "id": 121,
                "name": "SpaceX",
                "abbrev": "SpX",
                "countryCode": "USA",
                "type": 3,
                "infoURL": "http:\/\/www.spacex.com\/",
                "wikiURL": "http:\/\/en.wikipedia.org\/wiki\/SpaceX",
                "infoURLs": ["http:\/\/www.spacex.com\/"]
            }],
            "wikiURL": "https://en.wikipedia.org/wiki/Elon_Musk",
            "infoURLs": [],
            "infoURL": null,
            "imageSizes": [],
            "imageURL": "https://pbs.twimg.com/profile_images/782474226020200448/zDo-gAo0_400x400.jpg"
        },
        "missions": [{
            "id": null,
            "name": "IAC 2017",
            "description": "Elon Musk will be giving a presentation entitled \"Making Humans a Multi-Planetary Species\" about the updated ITS architecture at the International Astronautical Congress (IAC) 2017 in Adelaide, Australia. The presentation will take place at 14:00ACST / 04:30UTC on September 29th.",
            "type": 10,
            "typeName": "Communications"
        }]
    }],
    "offset": 0,
    "count": 1
}
